pii_scanner/__init__.py
pii_scanner/scanner.py
pii_scanner/constants/__init__.py
pii_scanner/constants/patterns_countries.py
pii_scanner/ner/__init__.py
pii_scanner/ner/ner_scanner.py
pii_scanner/regex_patterns/__init__.py
pii_scanner/regex_patterns/all_patterns.py
PIIScanner-0.1.2.dist-info/METADATA
PIIScanner-0.1.2.dist-info/WHEEL
PIIScanner-0.1.2.dist-info/top_level.txt
PIIScanner-0.1.2.dist-info/RECORD
