Metadata-Version: 2.1
Name: PIIScanner
Version: 0.1.2
Summary: A library for scanning Personally Identifiable Information (PII).
Home-page: https://github.com/devankit01/pii_scanner
Author: Ankit Gupta
Author-email: devankitgupta01@gmail.com
Classifier: Programming Language :: Python :: 3
Classifier: License :: OSI Approved :: MIT License
Classifier: Operating System :: OS Independent
Requires-Python: >=3.10
Requires-Dist: presidio-analyzer==2.2.32
